cyberfusion/RBLChecker/CLI.py
cyberfusion/RBLChecker/__init__.py
cyberfusion/RBLChecker/checkers.py
cyberfusion/RBLChecker/config.py
cyberfusion/RBLChecker/utilities.py
python3_cyberfusion_rblchecker-1.1.dist-info/METADATA
python3_cyberfusion_rblchecker-1.1.dist-info/WHEEL
python3_cyberfusion_rblchecker-1.1.dist-info/entry_points.txt
python3_cyberfusion_rblchecker-1.1.dist-info/top_level.txt
python3_cyberfusion_rblchecker-1.1.dist-info/RECORD
