Metadata-Version: 2.4
Name: python3-cyberfusion-rblchecker
Version: 1.1
Summary: Use rblchecker to check whether your outgoing mail IP addresses are listed on RBLs.
Author-email: Cyberfusion <support@cyberfusion.io>
Project-URL: Source, https://github.com/CyberfusionIO/python3-cyberfusion-rblchecker
Requires-Dist: docopt==0.6.2
Requires-Dist: schema==0.7.7
Requires-Dist: requests==2.32.3
Requires-Dist: netaddr==1.3.0
Requires-Dist: dnspython==2.7.0
Requires-Dist: PyYAML==6.0.2
